arctic_cod_detector-0.0.5.data/data/config/arctic-cod-detector/checkpoint
arctic_cod_detector-0.0.5.data/data/config/arctic-cod-detector/cnn.data-00000-of-00001
arctic_cod_detector-0.0.5.data/data/config/arctic-cod-detector/cnn.index
arctic_cod_detector-0.0.5.data/data/config/arctic-cod-detector/cnn.meta
bin/__init__.py
bin/run.py
arctic_cod_detector-0.0.5.dist-info/METADATA
arctic_cod_detector-0.0.5.dist-info/WHEEL
arctic_cod_detector-0.0.5.dist-info/entry_points.txt
arctic_cod_detector-0.0.5.dist-info/top_level.txt
arctic_cod_detector-0.0.5.dist-info/RECORD
