Metadata-Version: 2.1
Name: arctic-cod-detector
Version: 0.0.5
Summary: Neural-network detector of grunts made by arctic cod
Home-page: https://gitlab.meridian.cs.dal.ca/data_analytics_dal/projects/arctic_cod_detector
Author: Oliver Kirsebom, Fabio Frazao
Author-email: oliver.kirsebom@dal.ca, fsfrazao@dal.ca
License: GNU General Public License v3.0
Platform: UNKNOWN
Requires-Dist: ketos (==1.0.2)
